maliarov/__init__.py
maliarov/common.py
maliarov/webdriver.py
maliarov/data/desktop_user_agents.txt
maliarov/data/mobile_user_agents.txt
maliarov-0.2.5.dist-info/METADATA
maliarov-0.2.5.dist-info/WHEEL
maliarov-0.2.5.dist-info/top_level.txt
maliarov-0.2.5.dist-info/RECORD
