Metadata-Version: 2.1
Name: maliarov
Version: 0.2.5
Summary: Routine automation
Home-page: https://github.com/tlmy/webscraping
Author: Anatolii Maliarov
Author-email: tly.mov@gmail.com
License: UNKNOWN
Platform: UNKNOWN
Classifier: Programming Language :: Python :: 3.5
Classifier: Programming Language :: Python :: 3.6
Classifier: Programming Language :: Python :: 3.7
Classifier: License :: OSI Approved :: MIT License
Classifier: Operating System :: OS Independent
Requires-Dist: selenium (~=3.141.0)
Requires-Dist: datetime (~=4.3)
Requires-Dist: beautifulsoup4 (~=4.9.0)
Requires-Dist: urllib3 (~=1.25.9)
